sagemaker_shim/__init__.py
sagemaker_shim/app.py
sagemaker_shim/cli.py
sagemaker_shim/exceptions.py
sagemaker_shim/extract.py
sagemaker_shim/logging.py
sagemaker_shim/models.py
sagemaker_shim/vendor/__init__.py
sagemaker_shim/vendor/werkzeug/__init__.py
sagemaker_shim/vendor/werkzeug/security.py
sagemaker_shim-0.6.1.dist-info/licenses/LICENSE
sagemaker_shim-0.6.1.dist-info/METADATA
sagemaker_shim-0.6.1.dist-info/WHEEL
sagemaker_shim-0.6.1.dist-info/entry_points.txt
sagemaker_shim-0.6.1.dist-info/top_level.txt
sagemaker_shim-0.6.1.dist-info/RECORD
