Metadata-Version: 2.4
Name: sagemaker-shim
Version: 0.6.1
Summary: Adapts algorithms that implement the Grand Challenge inference API for running in SageMaker
Author: James Meakin
License: Apache-2.0
Project-URL: repository, https://github.com/DIAGNijmegen/rse-sagemaker-shim
Classifier: Development Status :: 3 - Alpha
Classifier: Intended Audience :: Developers
Requires-Python: ==3.12.*
License-File: LICENSE
Requires-Dist: fastapi!=0.89.0
Requires-Dist: uvicorn
Requires-Dist: click
Requires-Dist: aioboto3
Requires-Dist: botocore
Dynamic: license-file
